odoo/addons/sale_coupon_order_discount_fast_change_ui/__init__.py
odoo/addons/sale_coupon_order_discount_fast_change_ui/__manifest__.py
odoo/addons/sale_coupon_order_discount_fast_change_ui/i18n/es.po
odoo/addons/sale_coupon_order_discount_fast_change_ui/i18n/sale_coupon_order_discount_fast_change_ui.pot
odoo/addons/sale_coupon_order_discount_fast_change_ui/static/description/icon.png
odoo/addons/sale_coupon_order_discount_fast_change_ui/tests/__init__.py
odoo/addons/sale_coupon_order_discount_fast_change_ui/tests/test_sale_coupon_order_discount_fast_change.py
odoo/addons/sale_coupon_order_discount_fast_change_ui/wizard/__init__.py
odoo/addons/sale_coupon_order_discount_fast_change_ui/wizard/sale_order_discount_fast_change.py
odoo/addons/sale_coupon_order_discount_fast_change_ui/wizard/sale_order_discount_fast_change.xml
odoo14_addon_sale_coupon_order_discount_fast_change_ui-14.0.1.0.1.dev4.dist-info/METADATA
odoo14_addon_sale_coupon_order_discount_fast_change_ui-14.0.1.0.1.dev4.dist-info/WHEEL
odoo14_addon_sale_coupon_order_discount_fast_change_ui-14.0.1.0.1.dev4.dist-info/top_level.txt
odoo14_addon_sale_coupon_order_discount_fast_change_ui-14.0.1.0.1.dev4.dist-info/RECORD
